{
  "sneakers": [
    {
      "price": 12999,
      "name": "Мужские Кроссовки Nike Blazer Mid Suede",
      "avatar": "./src/img/sneakers/sneak-1.jpg",
      "id": "1"
    },
    {
      "price": 13299,
      "name": "Мужские Кроссовки Nike Air Max 270",
      "avatar": "./src/img/sneakers/sneak-2.jpg",
      "id": "2"
    },
    {
      "price": 8499,
      "name": "Мужские Кроссовки Nike Blazer Mid Suede",
      "avatar": "./src/img/sneakers/sneak-3.jpg",
      "id": "3"
    },
    {
      "price": 9699,
      "name": "Кроссовки Puma X Aka Boku Future Rider",
      "avatar": "./src/img/sneakers/sneak-4.jpg",
      "id": "4"
    },
    {
      "price": 13299,
      "name": "Мужские Кроссовки Nike Air Max 270",
      "avatar": "./src/img/sneakers/sneak-2.jpg",
      "id": "6"
    },
    {
      "price": 13299,
      "name": "Мужские Кроссовки Nike Air Max 270",
      "avatar": "./src/img/sneakers/sneak-2.jpg",
      "id": "7"
    }
  ],
  "cart": [
    {
      "price": 12999,
      "name": "Мужские Кроссовки Nike Blazer Mid Suede",
      "avatar": "./src/img/sneakers/sneak-1.jpg",
      "id": "1"
    },
    {
      "price": 13299,
      "name": "Мужские Кроссовки Nike Air Max 270",
      "avatar": "./src/img/sneakers/sneak-2.jpg",
      "id": "2"
    }
  ],
  "favorite": [
    {
      "price": 12999,
      "name": "Мужские Кроссовки Nike Blazer Mid Suede",
      "avatar": "./src/img/sneakers/sneak-1.jpg",
      "id": "1"
    },
    {
      "price": 13299,
      "name": "Мужские Кроссовки Nike Air Max 270",
      "avatar": "./src/img/sneakers/sneak-2.jpg",
      "id": "2"
    },
    {
      "price": 8499,
      "name": "Мужские Кроссовки Nike Blazer Mid Suede",
      "avatar": "./src/img/sneakers/sneak-3.jpg",
      "id": "3"
    }
  ],
  "orders": [
    {
      "id": "4b59",
      "item": [
        {
          "price": 12999,
          "name": "Мужские Кроссовки Nike Blazer Mid Suede",
          "avatar": "./src/img/sneakers/sneak-1.jpg",
          "id": "1"
        },
        {
          "price": 13299,
          "name": "Мужские Кроссовки Nike Air Max 270",
          "avatar": "./src/img/sneakers/sneak-2.jpg",
          "id": "2"
        }
      ]
    },
    {
      "id": "fc03",
      "item": [
        {
          "price": 12999,
          "name": "Мужские Кроссовки Nike Blazer Mid Suede",
          "avatar": "./src/img/sneakers/sneak-1.jpg",
          "id": "1"
        }
      ]
    }
  ]
}